{
    "Research_direction": "None",
    "Paper": "None",
    "Patent": "None",
    "Achievements": "None",
    "Class": "None",
    "Topic": "None",
    "Projects": "None",
    "Services_Activities": "None",
    "Award_status": "None",
    "Contact_information": "None",
    "Introduction": "张伟博. 副教授，硕士生导师。研究方向：媒介、文化与传播；品牌研究；文旅产业与城市形象研究。2017年毕业于澳门科技大学，获博士学位（PH.D）。中广协学术委员会委员（CAAAC）、澳门传播学会理事（CAM）。现任职于南京林业大学人文社会科学学院，兼任厦门大学新闻传播学院副教授。2008年、2010年两次参加 “中国教育部——日本电通基金项目”广告人才培训。2008-2010年担任中国广告艾菲奖（EFFIE AWARDS）编委。2014年-2015年赴台湾访学，2015年担任河海大学MBA中心导师。主持教育部人文社科规划基金项目、江苏省社科联重点项目、江苏高校哲学社会科学规划项目、南京市社会科学基金项目等多项课题。编著教材5部，发表学术论文近20篇。",
    "id": "0026",
    "img": "https://renwen.njfu.edu.cn/DFS//file/2021/09/26/20210926085903802pe9p79.jpg",
    "Department": "None",
    "Duties": "None",
    "Title": "None",
    "Category": "None",
    "Final_Education": "None",
    "Final_Degree": "None",
    "Work": "None",
    "Name": "张伟博",
    "Biographical_notes": "None",
    "Homepage": "None",
    "Professional_affiliations": "None",
    "Experience": "None"
}