{
    "Research_direction": "林业碳中和、数字林业、林产品贸易",
    "Paper": "重要论文成果<br/>[1] Zhai, J., Ning, Z., Dahal, R., & Yang, S. (2023). Wildfire Susceptibility of Land Use and Topographic Features in the Western United States: Implications for the Landscape Management. Forests, 14(4), 807.<br/>[2] Zhai, J., & Kuusela, O.-P. (2023). An EconometricStudy of Oregon’s Log and Lumber Markets: Estimation of Price ElasticitiesUsing Two Approaches. Forest Policy and Economics, 149, 102927.<br/>[3] Zhai, J., & Ning, Z. (2022). Models for the Economic Impacts of Forest Disturbances: A Systematic Review. Land, 11(9), 1608.<br/>[4] Zhai, J., & Kuusela, O. P. (2022).Incidence of domestic subsidies vs. export taxes: An equilibrium displacementmodel of log and lumber markets in Oregon. Forest Policy andEconomics, 135, 102647.<br/>[5] Rossi, D., Zhai, J., & Kuusela, O. P.(2021). Measuring the Value of Softwood Log Exports: Evidence from Oregon. Journalof Forestry, 119(4), 351-362.<br/>[6] Zhai, J., & Kuusela, O. P. (2020). EstimatingPrice Dynamics in the Aftermath of Forest Disturbances: The Biscuit Fire inSouthwest Oregon. Forest Science, 66(5),556-567.<br/><br/>[7] Zhai, J., Grebner, D. L., Grala, R. K., Fan, Z., &Munn, I. A. (2018). Contribution of ecological and socioeconomic factors to thepresence and abundance of invasive tree species in Mississippi, USA. Forests, 9(1),38.<br/>",
    "Patent": "None",
    "Achievements": "None",
    "Class": "环境经济理论与应用<br/>",
    "Topic": "None",
    "Projects": "None",
    "Services_Activities": "None",
    "Award_status": "None",
    "Contact_information": "zhaij@njfu.edu.cn",
    "Introduction": "None",
    "id": "0101",
    "img": "https://cem.njfu.edu.cn./UploadFile/photo/202307241538190011.jpg",
    "Department": "农林经济系",
    "Duties": "None",
    "Title": "None",
    "Category": "None",
    "Final_Education": "None",
    "Final_Degree": "None",
    "Work": "None",
    "Name": "翟郡",
    "Biographical_notes": "翟郡，女，1993年3月生，博士，美国俄勒冈州州立大学林业经济管理博士，现任南京林业大学经济管理学院讲师、南京林业大学数字林业与绿色发展研究院研究人员。<br/>长期从事林业经济管理、林业资源管理的综合研究和教学工作，聚焦林产品贸易、林业碳中和、数字林业等领域的理论与政策实践研究。主持国家自然科学基金青年项目1项，江苏省社会科学基金青年项目1项，中国博士后科学基金第73批面上项目1项。以第一作者发表多篇学术论文于本领域权威期刊《Forest Policy and Economics》《Forest Science》《Journal of Forestry》《Forests》等国外重要学术报刊，并参与教材编写和出版工作。<br/><br/><br/>一、学习经历<br/>2017-2021，俄勒冈州立大学（Oregon State University, USA），林业经济与政策专业，博士<br/>2015-2017，密西西比州立大学（Mississippi State University, USA），林业资源管理专业，硕士<br/>2011-2015，山东农业大学，林学专业，本科<br/><br/>二、工作经历<br/>2023.08-至今， 南京林业大学，数字林业与绿色发展研究院，研究人员<br/>2023.02-至今， 南京林业大学，经济管理学院，博士后<br/>2022.01-至今， 南京林业大学，经济管理学院，讲师<br/>2017.08-2021.08，俄勒冈州立大学，研究助理<br/>2015.08-2017.06，密西西比州立大学，研究助理<br/>",
    "Homepage": "None",
    "Professional_affiliations": "None",
    "Experience": "None"
}