{
    "Research_direction": "None",
    "Paper": "None",
    "Patent": "None",
    "Achievements": "None",
    "Class": "None",
    "Topic": "None",
    "Projects": "None",
    "Services_Activities": "None",
    "Award_status": "None",
    "Contact_information": "：yangfangwei@njfu.edu.cn",
    "Introduction": "None",
    "id": "0052",
    "img": "https://qg.njfu.edu.cn/DFS//file/2023/08/30/202308301825479946dqzd4.jpg?iid=64837",
    "Department": "None",
    "Duties": "None",
    "Title": "：讲师",
    "Category": "None",
    "Final_Education": "None",
    "Final_Degree": "None",
    "Work": "None",
    "Name": "杨方威",
    "Biographical_notes": "None",
    "Homepage": "None",
    "Professional_affiliations": "None",
    "Experience": "None"
}