{
    "Research_direction": "None",
    "Paper": "None",
    "Patent": "None",
    "Achievements": "None",
    "Class": "None",
    "Topic": "None",
    "Projects": "None",
    "Services_Activities": "None",
    "Award_status": "None",
    "Contact_information": "None",
    "Introduction": "None",
    "id": "0018",
    "img": "https://waiyuan.njfu.edu.cn/DFS//file/2023/09/04/20230904152828971gitnjp.jpg",
    "Department": "日语语言文学系<br/>日语语言文学系",
    "Duties": "<br/>",
    "Title": "教授<br/>教授",
    "Category": "None",
    "Final_Education": "None",
    "Final_Degree": "None",
    "Work": "None",
    "Name": "何宝年<br/>何宝年",
    "Biographical_notes": "None",
    "Homepage": "None",
    "Professional_affiliations": "None",
    "Experience": "None"
}