{
    "Research_direction": "光固化树脂<br/>生物基光固化增材制造材料<br/>",
    "Paper": "None",
    "Patent": "None",
    "Achievements": "[1] Cai Z. Study on the interfacial properties of viscous capillary flow of dilute acetic acid solutions of chitosan[J]. Carbohydrate Polymers, 2009<br/>[2]. Cai Z. Use of tung oil as a reactive toughening agent in dicyclopentadiene-terminated unsaturated polyester resins[J]. Industrial Crops and Products, 2013.<br/>[3] 朱新宝, 蔡正春. 基本化工工艺学教学实践与体会[J]. 化工高等教育, 2013(02):56-58.<br/>[4] Liu C, Wang C, Cai Z. Castor oil-based polyfunctional acrylate monomers: Synthesis and utilization in UV-curable materials[J]. Progress in Organic Coatings, Elsevier BV, 2018, 121: 236–246.<br/>[5] Zheng X, Cai Z, Lyu Z, . Synthesis of Si-containing macro-RAFT agent for the water-borne polyacrylate polyurethane with anti-graffiti coating applications[J]. Materials Today Communications, Elsevier BV, 2020, 25: 101590.<br/>",
    "Class": "化工工艺学<br/>工业催化<br/>精细化工实验<br/>合成树脂化学与应用（研）<br/>",
    "Topic": "None",
    "Projects": "None",
    "Services_Activities": "None",
    "Award_status": "None",
    "Contact_information": "办公longpan Road 157caizc@njfu.edu.cn",
    "Introduction": "蔡正春，江苏南京人，1978年3月生，博士，九三学社社员，讲师。2008年南京大学化学化工学院高分子物理与化学专业毕业并获博士学位。2008年9月入职南京林业大学化工院精细化工系。江苏省化学化工学会会员。<br/>",
    "id": "None",
    "img": "https://hg.njfu.edu.cn/DFS//file/2022/09/03/2022090314593647057fzui.jpg?iid=47807",
    "Department": "None",
    "Duties": "None",
    "Title": "None",
    "Category": "None",
    "Final_Education": "None",
    "Final_Degree": "None",
    "Work": "None",
    "Name": "蔡正春    Cai Zhengchun",
    "Biographical_notes": "None",
    "Homepage": "None",
    "Professional_affiliations": "None",
    "Experience": "None"
}